piconlib/__init__.py
piconlib/parse.py
piconlib/system.py
piconlib-0.0.6.dist-info/LICENSE
piconlib-0.0.6.dist-info/METADATA
piconlib-0.0.6.dist-info/WHEEL
piconlib-0.0.6.dist-info/top_level.txt
piconlib-0.0.6.dist-info/RECORD
