Metadata-Version: 2.1
Name: piconlib
Version: 0.0.6
Summary: A library to interact with Picon's system tree
Home-page: https://github.com/Tau5/piconlib
Author: Tau5
Author-email: tau0@tutanota.com
License: UNKNOWN
Platform: UNKNOWN
Classifier: Operating System :: OS Independent
Requires-Python: >=3.6
